Workbook

Sheet Visual Summary
B2: Ranking Tool
B4: Criteria Area | C4: Climate Smart Rice | D4: Shrimp | E4: Banana
B5: Economic Potential | C5: ='Smart Rice'!L32 -> 9 | D5: =Shrimp!L32 -> 8 | E5: =Banana!L32 -> 4.3333333
B6: Pro-Poor Potential | C6: ='Smart Rice'!L33 -> 8 | D6: =Shrimp!L33 -> 7.3333333 | E6: =Banana!L33 -> 6.6666667
B7: Green Growth Potential | C7: ='Smart Rice'!L34 -> 8 | D7: =Shrimp!L34 -> 6 | E7: =Banana!L34 -> 4.6666667
B8: Systemic Change Potential | C8: ='Smart Rice'!L35 -> 9.3333333 | D8: =Shrimp!L35 -> 8 | E8: =Banana!L35 -> 4.6666667
B9: PWD Opportunities | C9: ='Smart Rice'!L36 -> 2.6666667 | D9: =Shrimp!L36 -> 4.6666667 | E9: =Banana!L36 -> 6.6666667
B10: WEE Opportunitiies | C10: ='Smart Rice'!L37 -> 6.6666667 | D10: =Shrimp!L37 -> 7.3333333 | E10: =Banana!L37 -> 6.6666667
B11: Quick Win Potential | C11: ='Smart Rice'!L38 -> 8.1666667 | D11: =Shrimp!L38 -> 8.1666667 | E11: =Banana!L38 -> 5.1666667
B12: Total Score | C12: =SUM(C5:C11) -> 51.833333 | E12: =SUM(E5:E11) -> 38.833333
B72: Table 11. Weighted Score Against BASIN Criteria | C72: Total Points Available | D72: Premium Rice | E72: Shrimp | F72: Bananas
B73: Economic Potential | C73: 25 | D73: ='Smart Rice'!P32 -> 22.5 | E73: =Shrimp!P32 -> 20 | F73: =Banana!P32 -> 10.75
B74: Pro-Poor Potential | C74: 20 | D74: ='Smart Rice'!P33 -> 16 | E74: =Shrimp!P33 -> 14.6 | F74: =Banana!P33 -> 13.4
B75: Green Growth Potential | C75: 20 | D75: ='Smart Rice'!P34 -> 16 | E75: =Shrimp!P34 -> 12 | F75: =Banana!P34 -> 9.4
B76: Systemic Change Potential | C76: 10 | D76: ='Smart Rice'!P35 -> 9.3 | E76: =Shrimp!P35 -> 8 | F76: =Banana!P35 -> 4.7
B77: PWD Opportunities | C77: 5 | D77: ='Smart Rice'!P36 -> 1.35 | E77: =Shrimp!P36 -> 2.35 | F77: =Banana!P36 -> 3.35
B78: WEE Opportunitiies | C78: 10 | D78: ='Smart Rice'!P37 -> 6.7 | E78: =Shrimp!P37 -> 7.3 | F78: =Banana!P37 -> 6.7
B79: Quick Win Potential | C79: 10 | D79: ='Smart Rice'!P38 -> 8.2 | E79: =Shrimp!P38 -> 8.2 | F79: =Banana!P38 -> 5.2
B80: Total Score | C80: =SUM(C73:C79) -> 100 | D80: =SUM(D73:D79) -> 80.05 | E80: =SUM(E73:E79) -> 72.45 | F80: =SUM(F73:F79) -> 53.5

Sheet Smart Rice
C3: Ranking Tool | D3: ='Visual Summary'!C4 -> Climate Smart Rice
C4: INSTRUCTIONS: Researchers complete each box in green to indicate the engagement level of achievement against the following criteria. Please mark 3=High; 2=Medium; and 1=Low.
E5: 100 | J5: =D4 -> 0 | K5: =E5 -> 100
C6: ='Visual Summary'!B5 -> Economic Potential | D6: Score (1=low; 2=medium; 3=high) | E6: Weight | F6: Weighted Score | G6: Explanation | I6: ='Visual Summary'!B9 -> PWD Opportunities | J6: Score (1=low; 2=medium; 3=high) | K6: Weight | L6: Weighted Score | M6: Explanation
B7: 1 | C7: Market demand in domestic market | D7: 3 | E7: 30 | F7: =(((D7*E7)/3)) -> 30 | G7: Rice remains the staple food across Vietnam, and demand is consistent even during price fluctuations. Ecological and organic rice from the Mekong (e.g., ST25, ST24) is increasingly marketed to urban consumers in Hanoi and Ho Chi Minh City, where safety and branding drive price premiums | H7: 15 | I7: Scope to address barriers to promote persons with disability employment or entrepreneurship | J7: 1 | K7: 20 | L7: =(((J7*K7)/3)) -> 6.6666667 | M7: No evidence of targeted interventions for PWD inclusion in rice value chain
B8: 2 | C8: Opportunities for employment creation or income generation | D8: 2 | E8: 10 | F8: =(((D8*E8)/3)) -> 6.6666667 | G8: Mechanization has reduced on-farm labor demand, but cooperatives still create jobs in milling, seed production, and post-harvest handling. CSA demonstrations (alternate wetting/drying, 1M5R) also require farmer training and service provision, creating new forms of employment around input supply and technical services | H8: 16 | I8: Women and men with a disability have or can acquire skills required to engage in the value chain | J8: 1 | K8: 20 | L8: =(((J8*K8)/3)) -> 6.6666667 | M8: Skills training for PWD in rice is possible in processing roles but not documented
B9: 3 | C9: Profitability for target HHs | D9: 3 | E9: 10 | F9: =(((D9*E9)/3)) -> 10 | G9: Conventional triple-rice systems show diminishing returns due to soil degradation and higher fertilizer costs. In contrast, organic and ecological systems (rice-lotus, rice-shrimp) increase farmer income by 6–10 million VND/ha compared to conventional practices | H9: 17 | I9: Low entry barriers for persons with disability (e.g. value addition opportunities that do not have barriers for persons with a physical disability), social acceptance, low start-up costs, etc.) | J9: 1 | K9: 20 | L9: =(((J9*K9)/3)) -> 6.6666667 | M9: Rice farming involves physical labor and land, limiting low-barrier entry for PWD except in processing roles
B10: 4 | C10: Market demand for export market | D10: 3 | E10: 30 | F10: =(((D10*E10)/3)) -> 30 | G10: While rice exports represent ~70% of national output from the Delta, markets are shifting toward higher-quality, low-emission varieties. ST25 rice has won global awards, creating export momentum, but climate risks (salinity, erratic floods) undermine stable supply | H10: 18 | I10: Business interest or co-investment opportunity in working with target demographic | J10: 0 | K10: 20 | L10: =(((J10*K10)/3)) -> 0 | M10: No clear private investment interest in disability-focused rice models (field notes).
B11: 5 | C11: Strong potential for returns on investment for local or international investors | D11: 2 | E11: 20 | F11: =(((D11*E11)/3)) -> 13.333333 | G11: Buyers in both domestic and export markets already pay 3–5% premiums for climate-smart and low-emission rice. However, risks from climate shocks and contract instability (farmers breaking agreements when prices spike) mean that ROI is not guaranteed without stronger cooperative governance and traceability systems | H11: 19 | I11: Opportunity to collaborate or build upon existing efforts in area | J11: 1 | K11: 20 | L11: =(((J11*K11)/3)) -> 6.6666667 | M11: No existing initiatives for PWD in rice identified (field notes).
C12: Total | E12: =SUM(E7:E11) -> 100 | F12: =(SUM(F7:F11))/10 -> 9 | I12: Total | K12: =SUM(K7:K11) -> 100 | L12: =(SUM(L7:L11))/10 -> 2.6666667
C15: ='Visual Summary'!B6 -> Pro-Poor Potential | D15: Score (1=low; 2=medium; 3=high) | E15: Weight | F15: Weighted Score | G15: Explanation | I15: ='Visual Summary'!B10 -> WEE Opportunitiies | J15: Score (1=low; 2=medium; 3=high) | K15: Weight | L15: Weighted Score | M15: Explanation
B16: 6 | C16: Market systems have opportunities for people living in poverty/systemic barriers that the project can influence. | D16: 2 | E16: 20 | F16: =(((D16*E16)/3)) -> 13.333333 | G16: Ecological rice-shrimp and rice-lotus systems directly target poorer farmers because they require fewer chemical inputs and reduce risk from climate shocks. However, smallholders still face systemic barriers around credit and traceability — without certification or buyer links, they remain reliant on middlemen | H16: 20 | I16: Market systems have opportunities for women/systemic barriers that the project can influence (considering gender classification) | J16: 2 | K16: 20 | L16: =(((J16*K16)/3)) -> 13.333333 | M16: Women participate in planting, harvesting, and cooperative activities, but systemic barriers in land ownership persist
B17: 7 | C17: Low entry barriers for target poverty groups | D17: 2 | E17: 20 | F17: =(((D17*E17)/3)) -> 13.333333 | G17: Improved seed varieties and CSA practices are technically affordable, but poorer households often lack upfront cash or access to quality inputs. Financial institutions exist (VBSP and banks for the poor), but vulnerable households frequently resort to low-quality seed or fertilizer, undermining outcomes | H17: 21 | I17: High share of women employed in the value chain (scale of outreach) | J17: 2 | K17: 20 | L17: =(((J17*K17)/3)) -> 13.333333 | M17: Female labor is significant in rice cooperatives, though less visible in leadership or marketing roles
B18: 8 | C18: High share of target households already working in the value chain or interested in the value chain (scale of outreach | D18: 3 | E18: 20 | F18: =(((D18*E18)/3)) -> 20 | G18: Rice is grown by the majority of rural households in An Giang and across the Delta, often in cooperative structures. Even in shrimp-rice zones, households plant at least one rice crop per year, ensuring very high outreach scale | H18: 22 | I18: Low entry barriers for women (including with women with a disability, ethnic minority women) | J18: 3 | K18: 20 | L18: =(((J18*K18)/3)) -> 20 | M18: Tasks like planting and post-harvest involve women, making entry relatively accessible despite cultural barriers
B19: 9 | C19: Impact at scale - able to reach large number of people | D19: 3 | E19: 20 | F19: =(((D19*E19)/3)) -> 20 | G19: With ~18 million people in the Delta depending on rice, the outreach potential is wide. Moreover, urban consumers in Hanoi and HCMC are increasingly demanding safe and organic rice, linking smallholder production with broader market trends | H19: 23 | I19: Women control equipment/assets/resources required to participate. | J19: 1 | K19: 20 | L19: =(((J19*K19)/3)) -> 6.6666667 | M19: Land and assets (e.g., irrigation) remain mostly under male control, limiting women’s ownership
B20: 10 | C20: Transformative impact - clear and measurable pathways out of poverty | D20: 2 | E20: 20 | F20: =(((D20*E20)/3)) -> 13.333333 | G20: Income gains from organic and rice-shrimp systems are modest (6–10M VND/ha), but provide sustainability pathways | H20: 24 | I20: Increased incomes and agency potential for women in target communities | J20: 2 | K20: 20 | L20: =(((J20*K20)/3)) -> 13.333333 | M20: Cooperative participation offers women modest increases in income and decision-making agency
C21: Total | E21: =SUM(E16:E20) -> 100 | F21: =(SUM(F16:F20))/10 -> 8 | I21: Total | K21: =SUM(K16:K20) -> 100 | L21: =(SUM(L16:L20))/10 -> 6.6666667
C23: ='Visual Summary'!B7 -> Green Growth Potential | D23: Score (1=low; 2=medium; 3=high) | E23: Weight | F23: Weighted Score | G23: Explanation | I23: ='Visual Summary'!B11 -> Quick Win Potential | J23: Score (1=low; 2=medium; 3=high) | K23: Weight | L23: Weighted Score | M23: Explanation
B24: 6 | C24: Risk Perspective: Current level of resilience of the value chain to environmental factors and effects of climate change | D24: 1 | E24: 20 | F24: =(((D24*E24)/3)) -> 6.6666667 | G24: Triple-rice farming under high-dike systems interrupts natural flooding, which once replenished sediment and fertility. This has increased reliance on fertilizers, raised production costs, and degraded soil and water quality, leaving farmers highly vulnerable to droughts, salinity intrusion, and erratic rainfall | H24: 20 | I24: Systemic barriers/opportunities for target groups can be addressed in a shorter time frame | J24: 3 | K24: 10 | L24: =(((J24*K24)/3)) -> 10 | M24: Farmers identified that access to improved practices (like CSA techniques) and cooperative strengthening are immediate needs. These barriers could be tackled relatively quickly, since training and organizational support can be delivered within 12–18 months, though scaling to all households would take longer
B25: 7 | C25: Prospects for improving the resilience of the value chain to environmental factors and effects of climate change | D25: 3 | E25: 20 | F25: =(((D25*E25)/3)) -> 20 | G25: CSA practices like AWD (Alternate Wetting and Drying), 1M5R (one must, five reductions), and salt-tolerant varieties (e.g., ST24, ST25) have shown concrete results in reducing water use, methane emissions, and yield losses. Cooperatives piloting these methods reported significant uptake when paired with training and small incentives | H25: 21 | I25: There are interested market actors in solving the systemic barriers and/or capitalising on opportunities | J25: 3 | K25: 15 | L25: =(((J25*K25)/3)) -> 15 | M25: Companies like Tunlong and A An were cited as active buyers seeking ecological rice. This demonstrates that private buyers are already signaling demand for premium rice, creating clear opportunities to link farmers directly with markets
B26: 8 | C26: Negative impact perspective: Current impact of the value chain on the environment | D26: 3 | E26: 20 | F26: =(((D26*E26)/3)) -> 20 | G26: Conventional intensive rice emits methane and causes fertilizer runoff, contributing to greenhouse gas emissions and water pollution. Overuse of pesticides is also linked to health risks for farmers and declining biodiversity in the Delta | H26: 22 | I26: Current work being undertaken in the area (existing World Vision and other projects, relationships with market actors etc.) | J26: 3 | K26: 20 | L26: =(((J26*K26)/3)) -> 20 | M26: Field notes emphasize existing donor and NGO activities in the Mekong Delta on ecological farming, traceability, and certification. These provide a foundation that World Vision could build on, avoiding the need to start from scratch
B27: 9 | C27: Prospects for the commodity/ VC to restore environment or mitigate climate change | D27: 3 | E27: 20 | F27: =(((D27*E27)/3)) -> 20 | G27: Ecological farming systems such as rice–lotus or rice–shrimp rotations restore biodiversity by integrating aquatic species and reducing chemical inputs. Organic rice systems have been shown to improve soil fertility and water quality, while diversifying farmer income sources | H27: 23 | I27: Specific VC partners are readily engaging with INGOs and others to address complex challenges related to BASIN | J27: 2 | K27: 25 | L27: =(((J27*K27)/3)) -> 16.666667 | M27: Cooperatives are already working with NGOs and external actors, but their limited capacity weakens coordination and contract enforcement. Strengthening their role was seen as essential for farmers to reduce reliance on middlemen
B28: 10 | C28: Clean business interest to take green growth approach for private sector actors | D28: 2 | E28: 20 | F28: =(((D28*E28)/3)) -> 13.333333 | G28: Cooperatives adopting low-emission or premium rice varieties are attracting buyers willing to pay a 3–5% premium. Companies interested in sustainable branding see rice as part of their green transformation goals, though scale-up still depends on stronger traceability and certification systems | H28: 24 | I28: Existing and open platform to coordinate and manage a collective impact approach to a socioecomomic challenge | J28: 2 | K28: 30 | L28: =(((J28*K28)/3)) -> 20 | M28: cooperative unions, if better organized, could negotiate directly with buyers like Tunlong. This shows that platforms exist but need capacity building to truly function as collective action mechanisms
C29: Total | E29: =SUM(E24:E28) -> 100 | F29: =(SUM(F24:F28))/10 -> 8 | I29: Total | K29: =SUM(K24:K28) -> 100 | L29: =(SUM(L24:L28))/10 -> 8.1666667
C31: ='Visual Summary'!B8 -> Systemic Change Potential | D31: Score (1=low; 2=medium; 3=high) | E31: Weight | F31: Weighted Score | G31: Explanation | I31: Summary: Criteria Area | L31: Weighted Score | N31: WV Criteria | O31: MSD Tool Score | P31: Weighted Score
B32: 11 | C32: Co-investment (govt) Evidence of support to the value chain from the government and/or donors (e.g., having plans for investment, promotion policies and regulations are in place and effective) | D32: 3 | E32: 20 | F32: =(((D32*E32)/3)) -> 20 | G32: Farmers and cooperatives directly referenced Resolution 120’s role in supporting rice diversification and ecological farming in the Mekong Delta. The notes highlight that both government and donors are backing CSA pilots and cooperative strengthening, signaling strong institutional support | I32: =C6 -> Economic Potential | L32: =F12 -> 9 | N32: 25 | O32: 0.9 | P32: =N32*O32 -> 22.5
B33: 12 | C33: Co-investment - Availability and willingness of private market actors to invest in the value chain | D33: 3 | E33: 20 | F33: =(((D33*E33)/3)) -> 20 | G33: Local companies like Tunlong and A An were mentioned as active in contracting farmers and expressing demand for ecological rice. However, interviews also flagged that contract farming often breaks down when prices fluctuate, showing that while private interest exists, long-term investment is still fragile | I33: ='Visual Summary'!B6 -> Pro-Poor Potential | L33: =F21 -> 8 | N33: 20 | O33: 0.8 | P33: =N33*O33 -> 16
B34: 13 | C34: Market-based solution that can be sustained without the need of BASIN or other public-sector funding | D34: 2 | E34: 20 | F34: =(((D34*E34)/3)) -> 13.333333 | G34: Cooperative strengthening was emphasized as a pathway for farmers to contract directly with buyers, reducing dependence on middlemen. The field notes stressed that without such cooperative capacity, interventions rely heavily on NGO facilitation | I34: ='Visual Summary'!B7 -> Green Growth Potential | L34: =F29 -> 8 | N34: 20 | O34: 0.8 | P34: =N34*O34 -> 16
B35: 14 | C35: Scalability that can grow and reach other end-users (beyond project intervention area and timeframe) | D35: 3 | E35: 20 | F35: =(((D35*E35)/3)) -> 20 | G35: The ecological rice–shrimp rotation is widespread in lowland areas due to salinity and water constraints. Farmers see this system as scalable because it aligns with natural conditions and provides both ecological and income benefits, making it relevant beyond the pilot communes | I35: ='Visual Summary'!B8 -> Systemic Change Potential | L35: =F37 -> 9.3333333 | N35: 10 | O35: 0.93 | P35: =N35*O35 -> 9.3
B36: 15 | C36: Impact has potential to affect adjacent value chains and industries | D36: 3 | E36: 20 | F36: =(((D36*E36)/3)) -> 20 | G36: The rice–shrimp mix was specifically noted to have surprised the team by its ecological value. This model shows potential to influence aquaculture practices (by promoting ecological shrimp) and other crops that share water/soil systems | I36: ='Visual Summary'!B9 -> PWD Opportunities | L36: =L12 -> 2.6666667 | N36: 5 | O36: 0.27 | P36: =N36*O36 -> 1.35
C37: Total | E37: =SUM(E32:E36) -> 100 | F37: =(SUM(F32:F36))/10 -> 9.3333333 | I37: ='Visual Summary'!B10 -> WEE Opportunitiies | L37: =L21 -> 6.6666667 | N37: 10 | O37: 0.67 | P37: =N37*O37 -> 6.7
I38: ='Visual Summary'!B11 -> Quick Win Potential | L38: =L29 -> 8.1666667 | N38: 10 | O38: 0.82 | P38: =N38*O38 -> 8.2
O39: Total | P39: =SUM(P32:P38) -> 80.05

Sheet Banana
C3: Ranking Tool | D3: Banana
C4: INSTRUCTIONS: Researchers complete each box in green to indicate the engagement level of achievement against the following criteria. Please mark 3=High; 2=Medium; and 1=Low.
E5: 100 | J5: =D4 -> 0 | K5: =E5 -> 100
C6: ='Visual Summary'!B5 -> Economic Potential | D6: Score (0= NA 1=low; 2=medium; 3=high) | E6: Weight | F6: Weighted Score | G6: Explanation | I6: ='Visual Summary'!B9 -> PWD Opportunities | J6: Score (1=low; 2=medium; 3=high) | K6: Weight | L6: Weighted Score | M6: Explanation
B7: 1 | C7: Market demand in domestic market | D7: 1 | E7: 30 | F7: =(((D7*E7)/3)) -> 10 | G7: Bananas are consumed widely in Vietnam, but the specific local varieties grown in saline and freshwater-scarce areas are not favored in premium domestic markets like Hanoi or Ho Chi Minh City. Instead, most bananas from An Giang and nearby areas are sold to Cambodia, where demand exists for these varieties | H7: 15 | I7: Scope to address barriers to promote persons with disability employment or entrepreneurship | J7: 2 | K7: 20 | L7: =(((J7*K7)/3)) -> 13.333333 | M7: No targeted programs exist for PWD inclusion in banana farming. Handicraft potential.
B8: 2 | C8: Opportunities for employment creation or income generation | D8: 1 | E8: 10 | F8: =(((D8*E8)/3)) -> 3.3333333 | G8: Banana farming provides seasonal labor in cultivation and harvest, and women sometimes engage in post-harvest activities. Attempts to create handicrafts from banana trees have had limited success locally, but in Northern Vietnam companies export banana-based handicrafts to Europe, the US, and Japan, suggesting untapped opportunities if quality and design standards can be met | H8: 16 | I8: Women and men with a disability have or can acquire skills required to engage in the value chain | J8: 2 | K8: 20 | L8: =(((J8*K8)/3)) -> 13.333333 | M8: Possible but skill training for PWD in banana sector not identified in research
B9: 3 | C9: Profitability for target HHs | D9: 1 | E9: 10 | F9: =(((D9*E9)/3)) -> 3.3333333 | G9: Farmers face modest profits; without proper post-harvest management (especially for banana flower, which must be submerged in water to avoid spoilage), losses are common. While there is some demand for banana flour/banana flower in urban markets, the processing is mostly centralized in Ho Chi Minh City rather than locally, which limits rural producer margins | H9: 17 | I9: Low entry barriers for persons with disability (e.g. value addition opportunities that do not have barriers for persons with a physical disability), social acceptance, low start-up costs, etc.) | J9: 1 | K9: 20 | L9: =(((J9*K9)/3)) -> 6.6666667 | M9: Banana cultivation requires land access, physical labor for planting/harvesting, and sometimes heavy handling of banana flower. These factors raise entry barriers for people with physical disabilities. There is little evidence of alternative value-addition niches (e.g., handicraft work) being adapted to PWD needs locally
B10: 4 | C10: Market demand for export market | D10: 2 | E10: 30 | F10: =(((D10*E10)/3)) -> 20 | G10: Cambodia is currently the main export market, but this is not a reliable long-term opportunity since Cambodia can produce its own bananas. Regional buyers in Vietnam’s urban centers do purchase banana flower at high prices, but the market is niche, fresh-only, and logistics-sensitive | H10: 18 | I10: Business interest or co-investment opportunity in working with target demographic | J10: 1 | K10: 20 | L10: =(((J10*K10)/3)) -> 6.6666667 | M10: No buyers, processors, or handicraft firms reported interest in disability-specific banana initiatives. Unlike shrimp processing (where some factory lines may offer lower-barrier jobs), banana currently has no such targeted business models
B11: 5 | C11: Strong potential for returns on investment for local or international investors | D11: 1 | E11: 20 | F11: =(((D11*E11)/3)) -> 6.6666667 | G11: Returns on investment are possible, particularly with products like banana flower and handicrafts, but depend heavily on overcoming constraints like weak logistics, lack of traceability, and inconsistent product quality. Previous attempts with handicrafts and flour struggled because cooperatives and producers lacked direct buyer connections and reliable contracts, making ROI unpredictable and often low | H11: 19 | I11: Opportunity to collaborate or build upon existing efforts in area | J11: 0 | K11: 20 | L11: =(((J11*K11)/3)) -> 0 | M11: There are no existing disability-focused agricultural programs in the banana sector to build upon. This contrasts with other chains like vegetables, where some NGOs have piloted inclusive livelihood models. For bananas, inclusion would require new program design from scratch.
C12: Total | E12: =SUM(E7:E11) -> 100 | F12: =(SUM(F7:F11))/10 -> 4.3333333 | I12: Total | K12: =SUM(K7:K11) -> 100 | L12: =(SUM(L7:L11))/10 -> 4
C15: ='Visual Summary'!B6 -> Pro-Poor Potential | D15: Score (1=low; 2=medium; 3=high) | E15: Weight | F15: Weighted Score | G15: Explanation | I15: ='Visual Summary'!B10 -> WEE Opportunitiies | J15: Score (1=low; 2=medium; 3=high) | K15: Weight | L15: Weighted Score | M15: Explanation
B16: 6 | C16: Market systems have opportunities for people living in poverty/systemic barriers that the project can influence. | D16: 2 | E16: 20 | F16: =(((D16*E16)/3)) -> 13.333333 | G16: Poor farmers grow bananas, but systemic barriers like lack of finance and market access constrain income. | H16: 20 | I16: Market systems have opportunities for women/systemic barriers that the project can influence (considering gender classification) | J16: 2 | K16: 20 | L16: =(((J16*K16)/3)) -> 13.333333 | M16: Women can participate in banana production, though systemic barriers in land and markets remain
B17: 7 | C17: Low entry barriers for target poverty groups | D17: 2 | E17: 20 | F17: =(((D17*E17)/3)) -> 13.333333 | G17: Basic inputs and skills keep entry barriers low, but returns are modest without cooperative support. | H17: 21 | I17: High share of women employed in the value chain (scale of outreach) | J17: 2 | K17: 20 | L17: =(((J17*K17)/3)) -> 13.333333 | M17: Some women engage in farm and post-harvest roles, but overall share is modest compared to other crops
B18: 8 | C18: High share of target households already working in the value chain or interested in the value chain (scale of outreach | D18: 3 | E18: 20 | F18: =(((D18*E18)/3)) -> 20 | G18: Bananas are grown by many HHs, but mostly fragmented small plots limit outreach scale. | H18: 22 | I18: Low entry barriers for women (including with women with a disability, ethnic minority women) | J18: 3 | K18: 20 | L18: =(((J18*K18)/3)) -> 20 | M18: Cultivation skills are basic, so women (including ethnic minorities) can enter with few barriers
B19: 9 | C19: Impact at scale - able to reach large number of people | D19: 2 | E19: 20 | F19: =(((D19*E19)/3)) -> 13.333333 | G19: Banana cultivation is common but lacks aggregation or strong demand pull, limiting impact at scale. | H19: 23 | I19: Women control equipment/assets/resources required to participate. | J19: 1 | K19: 20 | L19: =(((J19*K19)/3)) -> 6.6666667 | M19: Land and equipment ownership is mostly male-dominated, limiting women’s control
B20: 10 | C20: Transformative impact - clear and measurable pathways out of poverty | D20: 1 | E20: 20 | F20: =(((D20*E20)/3)) -> 6.6666667 | G20: Banana rarely creates transformative poverty exits; incomes are supplementary, not life-changing. | H20: 24 | I20: Increased incomes and agency potential for women in target communities | J20: 2 | K20: 20 | L20: =(((J20*K20)/3)) -> 13.333333 | M20: Banana provides supplementary income that may increase women’s agency modestly
C21: Total | E21: =SUM(E16:E20) -> 100 | F21: =(SUM(F16:F20))/10 -> 6.6666667 | I21: Total | K21: =SUM(K16:K20) -> 100 | L21: =(SUM(L16:L20))/10 -> 6.6666667
C23: ='Visual Summary'!B7 -> Green Growth Potential | D23: Score (1=low; 2=medium; 3=high) | E23: Weight | F23: Weighted Score | G23: Explanation | I23: ='Visual Summary'!B11 -> Quick Win Potential | J23: Score (1=low; 2=medium; 3=high) | K23: Weight | L23: Weighted Score | M23: Explanation
B24: 6 | C24: Risk Perspective: Current level of resilience of the value chain to environmental factors and effects of climate change | D24: 2 | E24: 20 | F24: =(((D24*E24)/3)) -> 13.333333 | G24: Bananas can be grown multiple times per year and tolerate some climate variability, but in the saline and freshwater-scarce zones they are stressed and prone to disease outbreaks. Farmers noted that pests and fungal diseases are increasingly a problem in these areas | H24: 20 | I24: Systemic barriers/opportunities for target groups can be addressed in a shorter time frame | J24: 2 | K24: 10 | L24: =(((J24*K24)/3)) -> 6.6666667 | M24: Post-harvest handling (especially preventing banana flower from spoiling) is a clear short-term fix, as training and low-cost techniques already exist. Improving cooperative-level washing, storage, and transport could immediately reduce losses
B25: 7 | C25: Prospects for improving the resilience of the value chain to environmental factors and effects of climate change | D25: 2 | E25: 20 | F25: =(((D25*E25)/3)) -> 13.333333 | G25: There is recognition that using improved varieties and GAP (Good Agricultural Practices) could stabilize yields, but adoption is slow because smallholders lack financing and extension support. Where GAP training has been piloted, farmers reduced losses and improved quality, but scale remains limited | H25: 21 | I25: There are interested market actors in solving the systemic barriers and/or capitalising on opportunities | J25: 1 | K25: 15 | L25: =(((J25*K25)/3)) -> 5 | M25: Although small, there is genuine demand from Cambodian traders and some HCMC buyers for banana flower and raw bananas. These actors are interested in volume and quality improvements, but not yet in investing in logistics or certification. However, this could hurt banana producers in Cambodia as they struggle to compete on the market with products from Vietnam and Thailand in general.
B26: 8 | C26: Negative impact perspective: Current impact of the value chain on the environment | D26: 1 | E26: 20 | F26: =(((D26*E26)/3)) -> 6.6666667 | G26: Farmers often overuse fertilizers and pesticides because of limited access to training, which increases costs and degrades soil. This makes banana production less sustainable and more vulnerable over time (similar to the “low profitability” dynamic seen for rice) | H26: 22 | I26: Current work being undertaken in the area (existing World Vision and other projects, relationships with market actors etc.) | J26: 2 | K26: 20 | L26: =(((J26*K26)/3)) -> 13.333333 | M26: Fruit export programs (mango, dragon fruit) supported by donors and NGOs have built platforms (e.g., on traceability and GAP training) that banana farmers could “piggyback” on. However, bananas have not been the focus of such programs to date
B27: 9 | C27: Prospects for the commodity/ VC to restore environment or mitigate climate change | D27: 1 | E27: 20 | F27: =(((D27*E27)/3)) -> 6.6666667 | G27: There are precedents in Northern Vietnam where banana by-products are used for handicrafts and GAP-certified bananas target premium markets in Europe, the US, and Japan. These show potential environmental co-benefits (waste reuse, reduced chemicals), but in An Giang and the saline areas, cooperatives are too weak to meet certification requirements | H27: 23 | I27: Specific VC partners are readily engaging with INGOs and others to address complex challenges related to BASIN | J27: 2 | K27: 25 | L27: =(((J27*K27)/3)) -> 16.666667 | M27: Some cooperatives and traders are open to working with NGOs, but coordination is weak. Past attempts at cooperative upgrading (e.g., handicrafts, flour) faltered because middlemen relationships remained dominant and contracts were unreliable
B28: 10 | C28: Clean business interest to take green growth approach for private sector actors | D28: 1 | E28: 20 | F28: =(((D28*E28)/3)) -> 6.6666667 | G28: There is some niche interest in banana flower and handicrafts from buyers in Ho Chi Minh City and abroad, but investment is fragmented and small compared to other fruits like mango. Previous handicraft projects collapsed because producers lacked direct contracts and consistent volumes | H28: 24 | I28: Existing and open platform to coordinate and manage a collective impact approach to a socioecomomic challenge | J28: 1 | K28: 30 | L28: =(((J28*K28)/3)) -> 10 | M28: xport platforms created for other fruits (e.g., traceability portals, cooperative networks) could be extended to banana without starting from scratch. The challenge is ensuring consistent supply and quality, as current banana markets are fragmented
C29: Total | E29: =SUM(E24:E28) -> 100 | F29: =(SUM(F24:F28))/10 -> 4.6666667 | I29: Total | K29: =SUM(K24:K28) -> 100 | L29: =(SUM(L24:L28))/10 -> 5.1666667
C31: ='Visual Summary'!B8 -> Systemic Change Potential | D31: Score (1=low; 2=medium; 3=high) | E31: Weight | F31: Weighted Score | G31: Explanation | I31: Summary: Criteria Area | L31: Weighted Score | N31: WV Criteria | O31: MSD Tool Score | P31: Weighted Score
B32: 11 | C32: Co-investment (govt) Evidence of support to the value chain from the government and/or donors (e.g., having plans for investment, promotion policies and regulations are in place and effective) | D32: 2 | E32: 20 | F32: =(((D32*E32)/3)) -> 13.333333 | G32: While Vietnam’s government promotes fruit exports generally, interviews confirmed that bananas do not receive the same level of targeted support or branding as higher-value chains like mango or dragon fruit. In saline/freshwater-stressed zones, bananas are more of a fallback crop, so provincial investment is limited | I32: =C6 -> Economic Potential | L32: =F12 -> 4.3333333 | N32: 25 | O32: 0.43 | P32: =N32*O32 -> 10.75
B33: 12 | C33: Co-investment - Availability and willingness of private market actors to invest in the value chain | D33: 1 | E33: 20 | F33: =(((D33*E33)/3)) -> 6.6666667 | G33: Traders do buy bananas for sale to Cambodia and HCMC, but they operate on a small, opportunistic scale without significant investment in cold chain or processing. Unlike mangoes, there are few anchor firms offering long-term contracts or input support. | I33: ='Visual Summary'!B6 -> Pro-Poor Potential | L33: =F21 -> 6.6666667 | N33: 20 | O33: 0.67 | P33: =N33*O33 -> 13.4
B34: 13 | C34: Market-based solution that can be sustained without the need of BASIN or other public-sector funding | D34: 1 | E34: 20 | F34: =(((D34*E34)/3)) -> 6.6666667 | G34: Cooperatives and households often depend on NGO facilitation or ad hoc donor programs (e.g., handicraft pilots, banana flour promotion). Without these, producers revert to selling raw bananas to middlemen, which limits sustainability of interventions | I34: ='Visual Summary'!B7 -> Green Growth Potential | L34: =F29 -> 4.6666667 | N34: 20 | O34: 0.47 | P34: =N34*O34 -> 9.4
B35: 14 | C35: Scalability that can grow and reach other end-users (beyond project intervention area and timeframe) | D35: 1 | E35: 20 | F35: =(((D35*E35)/3)) -> 6.6666667 | G35: The crop can grow across the Mekong and into northern provinces, but poor logistics and weak aggregation systems prevent scaling into premium export markets. As noted, bananas from saline areas are not suitable for Japan and higher-value buyers, constraining scale to lower-value outlets | I35: ='Visual Summary'!B8 -> Systemic Change Potential | L35: =F37 -> 4.6666667 | N35: 10 | O35: 0.47 | P35: =N35*O35 -> 4.7
B36: 15 | C36: Impact has potential to affect adjacent value chains and industries | D36: 2 | E36: 20 | F36: =(((D36*E36)/3)) -> 13.333333 | G36: Upgrades in banana logistics, such as better cold storage or traceability systems, could directly benefit other fruit chains. For example, investments in aggregation for banana flour or flowers could be repurposed for mango or dragon fruit once supply chains mature. | I36: ='Visual Summary'!B9 -> PWD Opportunities | L36: =L21 -> 6.6666667 | N36: 5 | O36: 0.67 | P36: =N36*O36 -> 3.35
C37: Total | E37: =SUM(E32:E36) -> 100 | F37: =(SUM(F32:F36))/10 -> 4.6666667 | I37: ='Visual Summary'!B10 -> WEE Opportunitiies | L37: =L21 -> 6.6666667 | N37: 10 | O37: 0.67 | P37: =N37*O37 -> 6.7
I38: ='Visual Summary'!B11 -> Quick Win Potential | L38: =L29 -> 5.1666667 | N38: 10 | O38: 0.52 | P38: =N38*O38 -> 5.2
O39: Total | P39: =SUM(P32:P38) -> 53.5

Sheet Shrimp
C3: Ranking Tool | D3: ='Visual Summary'!D4 -> Shrimp
C4: INSTRUCTIONS: Researchers complete each box in green to indicate the engagement level of achievement against the following criteria. Please mark 3=High; 2=Medium; and 1=Low.
E5: 100 | J5: =D4 -> 0 | K5: =E5 -> 100
C6: ='Visual Summary'!B5 -> Economic Potential | D6: Score (0= NA 1=low; 2=medium; 3=high) | E6: Weight | F6: Weighted Score | G6: Explanation | I6: ='Visual Summary'!B9 -> PWD Opportunities | J6: Score (1=low; 2=medium; 3=high) | K6: Weight | L6: Weighted Score | M6: Explanation
B7: 1 | C7: Market demand in domestic market | D7: 3 | E7: 30 | F7: =(((D7*E7)/3)) -> 30 | G7: Shrimp produced in the project area is small and natural, making it less competitive in export markets. However, it is valued in large domestic cities like Hanoi and Ho Chi Minh City, where consumers pay a premium for ecological and safe products | H7: 15 | I7: Scope to address barriers to promote persons with disability employment or entrepreneurship | J7: 2 | K7: 20 | L7: =(((J8*K16)/3)) -> 13.333333 | M7: While no programs explicitly target persons with disabilities (PWD) in shrimp farming, the presence of small household-based shrimp processing facilities suggests an entry point. Processing involves tasks like cleaning, steaming, and sorting, which could potentially be adapted for PWD inclusion
B8: 2 | C8: Opportunities for employment creation or income generation | D8: 3 | E8: 10 | F8: =(((D8*E8)/3)) -> 10 | G8: Shrimp farming is labor-intensive and creates household-level income opportunities, while women are heavily engaged in shrimp processing. Small household-based processing facilities already exist, and with cooperative models, better equipment could expand jobs and raise earnings | H8: 16 | I8: Women and men with a disability have or can acquire skills required to engage in the value chain | J8: 2 | K8: 20 | L8: =(((J8*K17)/3)) -> 13.333333 | M8: Processing requires practical, task-specific skills rather than heavy physical labor, making it more accessible. With appropriate training, women and men with disabilities could acquire these skills and participate in local processing groups
B9: 3 | C9: Profitability for target HHs | D9: 2 | E9: 10 | F9: =(((D9*E9)/3)) -> 6.6666667 | G9: Profits depend heavily on production system. Naturally grown shrimp in rice–shrimp rotations generate income but are smaller and fetch lower prices, while intensified systems can increase profit but carry high risks of disease and input costs. Farmers with limited credit sometimes buy poor-quality larvae, leading to losses | H9: 17 | I9: Low entry barriers for persons with disability (e.g. value addition opportunities that do not have barriers for persons with a physical disability), social acceptance, low start-up costs, etc.) | J9: 2 | K9: 20 | L9: =(((J9*K18)/3)) -> 13.333333 | M9: Compared to pond farming, processing has lower capital requirements and could offer opportunities for PWD, particularly in cooperative-based models where tasks can be tailored.
B10: 4 | C10: Market demand for export market | D10: 2 | E10: 30 | F10: =(((D10*E10)/3)) -> 20 | G10: The shrimp produced in this area is generally too small for high-value export markets compared to intensified systems elsewhere. Buyers like Kamal and Baklio purchase shrimp, but mainly for domestic or lower-value markets, showing that export potential is constrained | H10: 18 | I10: Business interest or co-investment opportunity in working with target demographic | J10: 0 | K10: 20 | L10: =(((J10*K19)/3)) -> 0 | M10: At present, there’s no sign of private sector or cooperative investment specifically focused on disability inclusion in shrimp processing. Interest is centered on expanding processing capacity more generally
B11: 5 | C11: Strong potential for returns on investment for local or international investors | D11: 2 | E11: 20 | F11: =(((D11*E11)/3)) -> 13.333333 | G11: Investment opportunities exist, but risks are significant due to fluctuating market prices, disease, and contract instability. While there is potential in processing and ecological branding, investment appetite is cautious without stronger cooperative capacity and traceability systems | H11: 19 | I11: Opportunity to collaborate or build upon existing efforts in area | J11: 1 | K11: 20 | L11: =(((J11*K20)/3)) -> 6.6666667 | M11: If cooperatives are strengthened (as discussed in the notes), there is room to design inclusive processing models that involve PWD.
C12: Total | E12: =SUM(E7:E11) -> 100 | F12: =(SUM(F7:F11))/10 -> 8 | I12: Total | K12: =SUM(K7:K11) -> 100 | L12: =(SUM(L7:L11))/10 -> 4.6666667
C15: ='Visual Summary'!B6 -> Pro-Poor Potential | D15: Score (1=low; 2=medium; 3=high) | E15: Weight | F15: Weighted Score | G15: Explanation | I15: ='Visual Summary'!B10 -> WEE Opportunitiies | J15: Score (1=low; 2=medium; 3=high) | K15: Weight | L15: Weighted Score | M15: Explanation
B16: 6 | C16: Market systems have opportunities for people living in poverty/systemic barriers that the project can influence. | D16: 2 | E16: 20 | F16: =(((D16*E16)/3)) -> 13.333333 | G16: Shrimp is a key livelihood in the region, but vulnerable households face systemic barriers like lack of credit and reliance on middlemen. Farmers often break contracts when prices rise, while companies break them when prices fall, making markets unstable and limiting poor farmers’ bargaining power | H16: 20 | I16: Market systems have opportunities for women/systemic barriers that the project can influence (considering gender classification) | J16: 2 | K16: 20 | L16: =(((J16*K16)/3)) -> 13.333333 | M16: Women face systemic barriers in shrimp farming due to cultural norms and superstitions. Some communities hold the belief that women entering shrimp ponds bring bad luck, which restricts their direct involvement in production. However, women play a critical role in processing, where these taboos do not apply, offering a clear point of entry that programs like BASIN could influence
B17: 7 | C17: Low entry barriers for target poverty groups | D17: 1 | E17: 20 | F17: =(((D17*E17)/3)) -> 6.6666667 | G17: Entry requires ponds, seed, and feed, which are costly for the poorest households. Some support exists through banks for the poor, but limited capital often forces vulnerable farmers to buy poor-quality shrimp larvae, increasing risks of failure | H17: 21 | I17: High share of women employed in the value chain (scale of outreach) | J17: 3 | K17: 20 | L17: =(((J17*K17)/3)) -> 20 | M17: Women are heavily employed in shrimp processing, especially in steaming, cleaning, and sorting, which require significant labor. This indicates broad outreach potential, though concentrated in processing rather than production
B18: 8 | C18: High share of target households already working in the value chain or interested in the value chain (scale of outreach | D18: 3 | E18: 20 | F18: =(((D18*E18)/3)) -> 20 | G18: A large number of rural households in the lowland areas engage in shrimp–rice rotations. This makes shrimp one of the main value chains already practiced by target households, ensuring broad relevance for outreach | H18: 22 | I18: Low entry barriers for women (including with women with a disability, ethnic minority women) | J18: 3 | K18: 20 | L18: =(((J18*K18)/3)) -> 20 | M18: Processing tasks require practical skills that are easily transferable and do not demand significant capital, making them accessible to women, including ethnic minority women. However, entry into farming itself is constrained by both superstition and land/asset access
B19: 9 | C19: Impact at scale - able to reach large number of people | D19: 3 | E19: 20 | F19: =(((D19*E19)/3)) -> 20 | G19: Given shrimp’s importance in the Delta, interventions can reach a large population. Scaling ecological shrimp production could create widespread benefits in both income and environmental resilience | H19: 23 | I19: Women control equipment/assets/resources required to participate. | J19: 1 | K19: 20 | L19: =(((J19*K19)/3)) -> 6.6666667 | M19: Women rarely control ponds, land, or the larger equipment needed for shrimp farming. Ownership and decision-making power remain male-dominated, limiting women’s influence over the most profitable parts of the chain
B20: 10 | C20: Transformative impact - clear and measurable pathways out of poverty | D20: 2 | E20: 20 | F20: =(((D20*E20)/3)) -> 13.333333 | G20: Successful shrimp farmers can achieve higher incomes, especially when linked to ecological branding for urban consumers. However, disease outbreaks and contract instability often push households back into debt, limiting clear and consistent pathways out of poverty | H20: 24 | I20: Increased incomes and agency potential for women in target communities | J20: 2 | K20: 20 | L20: =(((J20*K20)/3)) -> 13.333333 | M20: Processing provides women with supplemental income and strengthens their role in household livelihoods. With cooperative strengthening and fairer contracts, women could see expanded income opportunities and greater agency in community decision-making
C21: Total | E21: =SUM(E16:E20) -> 100 | F21: =(SUM(F16:F20))/10 -> 7.3333333 | I21: Total | K21: =SUM(K16:K20) -> 100 | L21: =(SUM(L16:L20))/10 -> 7.3333333
C23: ='Visual Summary'!B7 -> Green Growth Potential | D23: Score (1=low; 2=medium; 3=high) | E23: Weight | F23: Weighted Score | G23: Explanation | I23: ='Visual Summary'!B11 -> Quick Win Potential | J23: Score (1=low; 2=medium; 3=high) | K23: Weight | L23: Weighted Score | M23: Explanation
B24: 6 | C24: Risk Perspective: Current level of resilience of the value chain to environmental factors and effects of climate change | D24: 2 | E24: 20 | F24: =(((D24*E24)/3)) -> 13.333333 | G24: Shrimp production in the project area is highly vulnerable to salinity intrusion, freshwater shortages, and disease outbreaks. Natural shrimp grown in rice–shrimp systems are small and less competitive, but they align better with ecological conditions than intensified farming, which has proven riskier | H24: 20 | I24: Systemic barriers/opportunities for target groups can be addressed in a shorter time frame | J24: 3 | K24: 10 | L24: =(((J24*K24)/3)) -> 10 | M24: Shrimp farmers face clear, addressable barriers such as access to quality larvae, credit, and reliable contracts. BASIN could realistically work within 12–18 months to improve cooperative management, farmer–buyer links, and basic processing facilities, all of which were highlighted as weak points
B25: 7 | C25: Prospects for improving the resilience of the value chain to environmental factors and effects of climate change | D25: 2 | E25: 20 | F25: =(((D25*E25)/3)) -> 13.333333 | G25: Rice–shrimp rotations make better use of low-lying, saline-prone land, reducing vulnerability and aligning with ecological farming. These systems produce “natural” shrimp and rice that urban consumers perceive as safer, suggesting resilience and market value can be strengthened if better organized | H25: 21 | I25: There are interested market actors in solving the systemic barriers and/or capitalising on opportunities | J25: 3 | K25: 15 | L25: =(((J25*K25)/3)) -> 15 | M25: Buyers such as Kamal and Baklio are already purchasing shrimp, and companies like Tunlong (in rice–shrimp integration) have shown willingness to pay premiums for ecological products. Monterray Bay open to leveraging their international buyer relationships like Wal Mart. This suggests that there are market actors ready to engage if BASIN helps de-risk supply
B26: 8 | C26: Negative impact perspective: Current impact of the value chain on the environment | D26: 2 | E26: 20 | F26: =(((D26*E26)/3)) -> 13.333333 | G26: Intensified shrimp farming elsewhere in the Delta has caused water pollution and overuse of poor-quality inputs. Even in the field area, limited access to good larvae and credit pushes farmers into risky practices that undermine both environmental quality and productivity | H26: 22 | I26: Current work being undertaken in the area (existing World Vision and other projects, relationships with market actors etc.) | J26: 3 | K26: 20 | L26: =(((J26*K26)/3)) -> 20 | M26: The notes show that World Vision and other actors have already been working in the region on ecological production and cooperative strengthening. BASIN could plug into these initiatives instead of starting from scratch, ensuring continuity and faster results
B27: 9 | C27: Prospects for the commodity/ VC to restore environment or mitigate climate change | D27: 3 | E27: 20 | F27: =(((D27*E27)/3)) -> 20 | G27: Ecological shrimp production, especially in rotation with rice, contributes positively by using natural flood regimes and lowering chemical input use. This system surprised the team with its ecological value and potential to support climate change mitigation strategies | H27: 23 | I27: Specific VC partners are readily engaging with INGOs and others to address complex challenges related to BASIN | J27: 2 | K27: 25 | L27: =(((J27*K27)/3)) -> 16.666667 | M27: Specific VC partners are readily engaging with INGOs and others to address complex challenges related to BASIN. Monterray Bay could help too.
B28: 10 | C28: Clean business interest to take green growth approach for private sector actors | E28: 20 | F28: =(((D28*E28)/3)) -> 0 | G28: While not yet mainstream, there is demand from domestic consumers in major cities like Hanoi and Ho Chi Minh City for ecologically grown shrimp. Buyers are willing to pay premiums for products marketed as natural or safe, suggesting opportunities for clean growth if traceability and cooperative structures are strengthened | H28: 24 | I28: Existing and open platform to coordinate and manage a collective impact approach to a socioecomomic challenge | J28: 2 | K28: 30 | L28: =(((J28*K28)/3)) -> 20 | M28: Cooperative unions and ecological rice–shrimp systems already act as informal coordination platforms. BASIN could formalize these into collective impact structures, linking farmers, buyers, and technical actors under a shared sustainability and market-driven agenda
C29: Total | E29: =SUM(E24:E28) -> 100 | F29: =(SUM(F24:F28))/10 -> 6 | I29: Total | K29: =SUM(K24:K28) -> 100 | L29: =(SUM(L24:L28))/10 -> 8.1666667
C31: ='Visual Summary'!B8 -> Systemic Change Potential | D31: Score (1=low; 2=medium; 3=high) | E31: Weight | F31: Weighted Score | G31: Explanation | I31: Summary: Criteria Area | L31: Weighted Score | N31: WV Criteria | O31: MSD Tool Score | P31: Weighted Score
B32: 11 | C32: Co-investment (govt) Evidence of support to the value chain from the government and/or donors (e.g., having plans for investment, promotion policies and regulations are in place and effective) | D32: 3 | E32: 20 | F32: =(((D32*E32)/3)) -> 20 | G32: The Department of Agriculture and Rural Development (DARD) provides technical support to shrimp farmers and some small pilots. However, there is no evidence of a large-scale Green Food Program (GFP) or broad provincial investment in sustainable shrimp. Current support is piecemeal and not yet at the level of systemic transformatio | I32: =C6 -> Economic Potential | L32: =F12 -> 8 | N32: 25 | O32: 0.8 | P32: =N32*O32 -> 20
B33: 12 | C33: Co-investment - Availability and willingness of private market actors to invest in the value chain | D33: 3 | E33: 20 | F33: =(((D33*E33)/3)) -> 20 | G33: buyers exist (e.g., Kamal, Baklio) and urban demand for ecological shrimp is real, but few private firms are making large-scale investments in scaling sustainable shrimp systems. Partnerships with actors like Fresh Studio or Monterey Bay Aquarium are intrested in co-investment and partnership opportunities. | I33: ='Visual Summary'!B6 -> Pro-Poor Potential | L33: =F21 -> 7.3333333 | N33: 20 | O33: 0.73 | P33: =N33*O33 -> 14.6
B34: 13 | C34: Market-based solution that can be sustained without the need of BASIN or other public-sector funding | D34: 2 | E34: 20 | F34: =(((D34*E34)/3)) -> 13.333333 | G34: Local markets in big cities (Hanoi, Ho Chi Minh City) sustain demand for naturally grown shrimp when marketed as ecological or safe. However, systems for certification, traceability, and export standards are absent in the field area, meaning that long-term sustainability still depends on NGO or donor facilitation | I34: ='Visual Summary'!B7 -> Green Growth Potential | L34: =F29 -> 6 | N34: 20 | O34: 0.6 | P34: =N34*O34 -> 12
B35: 14 | C35: Scalability that can grow and reach other end-users (beyond project intervention area and timeframe) | D35: 2 | E35: 20 | F35: =(((D35*E35)/3)) -> 13.333333 | G35: Eological rice–shrimp systems are widely practiced in the low-lying Delta and have natural scaling potential. Yet constraints like poor hatchery infrastructure and inconsistent seed quality limit expansion. Without stronger hatchery and certification systems, scaling will remain incremental | I35: ='Visual Summary'!B8 -> Systemic Change Potential | L35: =F37 -> 8 | N35: 10 | O35: 0.8 | P35: =N35*O35 -> 8
B36: 15 | C36: Impact has potential to affect adjacent value chains and industries | D36: 2 | E36: 20 | F36: =(((D36*E36)/3)) -> 13.333333 | G36: The ecological rice–shrimp model does show influence on rice farming practices (e.g., reducing chemical inputs) and could inform integrated aquaculture approaches. | I36: ='Visual Summary'!B9 -> PWD Opportunities | L36: =L12 -> 4.6666667 | N36: 5 | O36: 0.47 | P36: =N36*O36 -> 2.35
C37: Total | E37: =SUM(E32:E36) -> 100 | F37: =(SUM(F32:F36))/10 -> 8 | I37: ='Visual Summary'!B10 -> WEE Opportunitiies | L37: =L21 -> 7.3333333 | N37: 10 | O37: 0.73 | P37: =N37*O37 -> 7.3
I38: ='Visual Summary'!B11 -> Quick Win Potential | L38: =L29 -> 8.1666667 | N38: 10 | O38: 0.82 | P38: =N38*O38 -> 8.2
O39: Total | P39: =SUM(P32:P38) -> 72.45
